atikin_data/__init__.py
atikin_data/auto_convert.py
atikin_data/cli.py
atikin_data/column_stats.py
atikin_data/filter_rows.py
atikin_data/frame.py
atikin_data/io.py
atikin_data/merge_files.py
atikin_data/missing_report.py
atikin_data/quick_preview.py
atikin_data/quick_summary.py
atikin_data/sort_columns.py
atikin_data/visual_summary.py
atikin_data-0.1.0.dist-info/licenses/LICENSE
atikin_data-0.1.0.dist-info/METADATA
atikin_data-0.1.0.dist-info/WHEEL
atikin_data-0.1.0.dist-info/entry_points.txt
atikin_data-0.1.0.dist-info/top_level.txt
atikin_data-0.1.0.dist-info/RECORD
