Metadata-Version: 2.4
Name: atikin-data
Version: 0.1.0
Summary: Atikin-Data — lightweight smart data toolkit (mini-pandas style utilities for daily use)
Author-email: Atikin Verse <atikinverse@gmail.com>
License: MIT
Keywords: data,csv,json,excel,lightweight,atikin
Classifier: Programming Language :: Python :: 3
Classifier: License :: OSI Approved :: MIT License
Classifier: Operating System :: OS Independent
Requires-Python: >=3.8
License-File: LICENSE
Provides-Extra: excel
Requires-Dist: openpyxl; extra == "excel"
Provides-Extra: pandas
Requires-Dist: pandas; extra == "pandas"
Dynamic: license-file
